lsp_cli/__init__.py
lsp_cli/__main__.py
lsp_cli/cli/__init__.py
lsp_cli/cli/definition.py
lsp_cli/cli/hover.py
lsp_cli/cli/locate.py
lsp_cli/cli/main.py
lsp_cli/cli/options.py
lsp_cli/cli/outline.py
lsp_cli/cli/reference.py
lsp_cli/cli/rename.py
lsp_cli/cli/search.py
lsp_cli/cli/shared.py
lsp_cli/cli/symbol.py
lsp_cli/client.py
lsp_cli/manager/__init__.py
lsp_cli/manager/__main__.py
lsp_cli/manager/capability.py
lsp_cli/manager/client.py
lsp_cli/manager/manager.py
lsp_cli/manager/models.py
lsp_cli/manager/server.py
lsp_cli/server.py
lsp_cli/settings.py
lsp_cli/utils/__init__.py
lsp_cli/utils/http.py
lsp_cli/utils/socket.py
lsp_cli/utils/sync.py
lsp_cli-0.1.1.dist-info/WHEEL
lsp_cli-0.1.1.dist-info/entry_points.txt
lsp_cli-0.1.1.dist-info/METADATA
lsp_cli-0.1.1.dist-info/RECORD
