Metadata-Version: 2.3
Name: lsp-cli
Version: 0.1.1
Summary: A powerful command-line interface for the Language Server Agent Protocol (LSAP)
Keywords: Language Server Protocol,LSP,CLI,Developer Tools,LSAP
Author: observerw
Author-email: observerw <wozluohd@gmail.com>
Classifier: Programming Language :: Python
Classifier: Programming Language :: Python :: 3.13
Classifier: License :: OSI Approved :: MIT License
Classifier: Operating System :: POSIX :: Linux
Classifier: Operating System :: MacOS
Requires-Dist: anyio>=4.12.0
Requires-Dist: asyncer>=0.0.12
Requires-Dist: attrs>=25.4.0
Requires-Dist: httpx>=0.28.1
Requires-Dist: loguru>=0.7.3
Requires-Dist: platformdirs>=4.5.1
Requires-Dist: pydantic>=2.12.5
Requires-Dist: pydantic-settings>=2.12.0
Requires-Dist: typer>=0.20.1
Requires-Dist: uvicorn>=0.40.0
Requires-Dist: litestar>=2.19.0
Requires-Dist: xxhash>=3.6.0
Requires-Dist: tenacity>=9.1.2
Requires-Dist: lsp-client>=0.3.0
Requires-Dist: lsap-sdk>=0.1.0
Requires-Python: >=3.13
